truck_factor_gdeluisi/__init__.py
truck_factor_gdeluisi/helper.py
truck_factor_gdeluisi/main.py
truck_factor_gdeluisi/data/ext.json
truck_factor_gdeluisi-1.2.4.dist-info/METADATA
truck_factor_gdeluisi-1.2.4.dist-info/WHEEL
truck_factor_gdeluisi-1.2.4.dist-info/entry_points.txt
truck_factor_gdeluisi-1.2.4.dist-info/licenses/LICENSE
truck_factor_gdeluisi-1.2.4.dist-info/RECORD
