Metadata-Version: 2.4
Name: truck-factor-gdeluisi
Version: 1.2.4
Summary: Simple library for truck factor calculation
Author-email: Gerardo De Luisi <deluisigerardo@gmail.com>
License-File: LICENSE
Keywords: git,projects,truck factor
Classifier: License :: OSI Approved :: GNU General Public License v3 or later (GPLv3+)
Classifier: Operating System :: OS Independent
Classifier: Programming Language :: Python :: 3.10
Classifier: Programming Language :: Python :: 3.11
Classifier: Programming Language :: Python :: 3.12
Classifier: Programming Language :: Python :: 3.13
Requires-Python: >=3.10
Requires-Dist: pandas
